MANIFEST.in
README.txt
setup.cfg
setup.py
src/requires.txt
src/m3_logview/__init__.py
src/m3_logview/actions.py
src/m3_logview/app_meta.py
src/m3_logview/forms.py
src/m3_logview/helpers.py
src/m3_logview.egg-info/PKG-INFO
src/m3_logview.egg-info/SOURCES.txt
src/m3_logview.egg-info/dependency_links.txt
src/m3_logview.egg-info/top_level.txt
src/m3_logview/templates/ui-js/logview.js
src/tests/__init__.py
src/tests/manage.py
src/tests/prepare_env.py
src/tests/settings.py
src/tests/shell.sh
src/tests/test.sh
src/tests/urls.py
src/tests/version.py
src/tests/core/__init__.py
src/tests/core/tests.py