Metadata-Version: 1.1
Name: m3-logview
Version: 2.0.0
Summary: Просмотр логов в интерфейсе администратора
Home-page: https://bitbucket.org/barsgroup/m3-logview
Author: BARS Group
Author-email: bars@bars-open.ru
License: MIT
Platform: UNKNOWN
Classifier: Intended Audience :: Developers
Classifier: Environment :: Web Environment
Classifier: Natural Language :: Russian
Classifier: Natural Language :: English
Classifier: Operating System :: OS Independent
Classifier: Programming Language :: Python
Classifier: License :: OSI Approved :: MIT License
Classifier: Development Status :: 5 - Production/Stable
